git_bak/__init__.py
git_bak/args.py
git_bak/exceptions.py
git_bak/git.py
git_bak/handlers.py
git_bak/logging.py
git_bak/main.py
git_bak/requests.py
git_bak/runners.py
git_bak-0.2.0.dist-info/METADATA
git_bak-0.2.0.dist-info/WHEEL
git_bak-0.2.0.dist-info/entry_points.txt
git_bak-0.2.0.dist-info/licenses/LICENSE
git_bak-0.2.0.dist-info/RECORD
