Metadata-Version: 2.4
Name: git-bak
Version: 0.2.0
Summary: Git-Bak is a backup/restore cli for local Git repositories.
Project-URL: Homepage, https://github.com/khojbjerg/git-bak
Author: Kasper Hojbjerg
License-File: LICENSE
Requires-Python: >=3.12
